{
  "pools": [
    {
      "rolls": 1,
      "entries": [
        {
          "type": "minecraft:item",
          "name": "minecraft:warped_fungus_on_a_stick",
          "functions": [
            {
              "function": "minecraft:set_name",
              "entity": "this",
              "name": {
                "translate": "item.jinxed.sacrificial_book",
                "bold": false,
                "italic": false,
                "underlined": false,
                "strikethrough": false,
                "obfuscated": false
              }
            },
            {
              "function": "minecraft:set_lore",
              "entity": "this",
              "lore": [
                {
                  "translate": "item.jinxed.sacrificial_book.desc",
                  "bold": false,
                  "italic": false,
                  "underlined": false,
                  "strikethrough": false,
                  "obfuscated": false
                },
                {
                  "translate": "pack.jinxed",
                  "color": "red",
                  "bold": false,
                  "italic": false,
                  "underlined": false,
                  "strikethrough": false,
                  "obfuscated": false
                }
              ]
            },
            {
              "function": "minecraft:set_nbt",
              "tag": "{CustomModelData:8,jinxed:{id:\"sacrificial_guide\"},RepairCost:999,Unbreakable:1b,HideFlags:4}"
            }
          ]
        }
      ]
    }
  ]
}